comicwalker_downloader/__init__.py
comicwalker_downloader/__main__.py
comicwalker_downloader/_version.py
comicwalker_downloader/cli.py
comicwalker_downloader/comic_downloader.py
comicwalker_downloader/comic_parser.py
comicwalker_downloader/exceptions.py
comicwalker_downloader/utils.py
cowado-0.1.3.dist-info/METADATA
cowado-0.1.3.dist-info/WHEEL
cowado-0.1.3.dist-info/entry_points.txt
cowado-0.1.3.dist-info/top_level.txt
cowado-0.1.3.dist-info/RECORD
