Metadata-Version: 2.4
Name: cowado
Version: 0.1.3
Summary: Download manga from ComicWalker
Author-email: Timolio <timbad77777@gmail.com>
License: MIT
Project-URL: Homepage, https://github.com/Timolio/ComicWalkerDownloader
Keywords: comic,manga,downloader,comicwalker,cowado
Requires-Python: >=3.8
Requires-Dist: fire
Requires-Dist: requests
Requires-Dist: beautifulsoup4
Requires-Dist: tqdm
Requires-Dist: colorama
Requires-Dist: InquirerPy
Requires-Dist: loguru
